LICENSE
MANIFEST.in
README.md
requirements.txt
setup.py
eve_tools/__init__.py
eve_tools.egg-info/PKG-INFO
eve_tools.egg-info/SOURCES.txt
eve_tools.egg-info/dependency_links.txt
eve_tools.egg-info/requires.txt
eve_tools.egg-info/top_level.txt
eve_tools/ESI/__init__.py
eve_tools/ESI/application.py
eve_tools/ESI/esi.py
eve_tools/ESI/metadata.py
eve_tools/ESI/param.py
eve_tools/ESI/token.py
eve_tools/ESI/utils.py
eve_tools/ESI/sso/application.json
eve_tools/ESI/sso/esi_oauth_native.py
eve_tools/ESI/sso/refresh_token.py
eve_tools/ESI/sso/shared_flow.py
eve_tools/ESI/sso/utils.py
eve_tools/ESI/sso/validate_jwt.py
eve_tools/api/__init__.py
eve_tools/api/check.py
eve_tools/api/market.py
eve_tools/api/search.py
eve_tools/api/utils.py
eve_tools/config/__init__.py
eve_tools/config/paths.py
eve_tools/data/__init__.py
eve_tools/data/cache.py
eve_tools/data/db.py
eve_tools/data/dbconfig.yaml
eve_tools/data/static/invTypes.csv.bz2
eve_tools/data/static/invVolumes.csv.bz2
eve_tools/data/static/mapRegions.csv.bz2
eve_tools/data/static/mapSolarSystems.csv.bz2
eve_tools/data/static/staStations.csv.bz2
eve_tools/tests/__init__.py
eve_tools/tests/test_api.py
eve_tools/tests/test_data.py
eve_tools/tests/test_esi.py
eve_tools/tests/testconfig.yaml
eve_tools/tests/utils.py