Metadata-Version: 2.1
Name: eve-tools
Version: 0.1.2
Summary: Tools collection for EVE game plays.
Home-page: UNKNOWN
Author: Hanbo
Author-email: hb.evetools@gmail.com
License: BSD 3-Clause License
Keywords: python,esi,eveonline
Platform: UNKNOWN
Classifier: Development Status :: 2 - Pre-Alpha
Classifier: Programming Language :: Python :: 3.7
Classifier: Programming Language :: Python :: 3.8
Classifier: Programming Language :: Python :: 3.9
Classifier: Programming Language :: Python :: 3.10
Classifier: Intended Audience :: Developers
